omnicart_pipeline/__init__.py
omnicart_pipeline/api_client.py
omnicart_pipeline/cli.py
omnicart_pipeline/config.py
omnicart_pipeline/data_analyzer.py
omnicart_pipeline/data_enricher.py
omnicart_pipeline/pipeline.cfg
omnicart_pipeline/pipeline.py
omnicart_pipeline_campeon-0.1.5.dist-info/entry_points.txt
omnicart_pipeline_campeon-0.1.5.dist-info/METADATA
omnicart_pipeline_campeon-0.1.5.dist-info/WHEEL
omnicart_pipeline_campeon-0.1.5.dist-info/RECORD
