Metadata-Version: 2.4
Name: omnicart-pipeline-campeon
Version: 0.1.5
Summary: This is a package that run an ETL pipeline to fetch data from an API, enrich it and generate a summary analysis
Author: Oluwaseyi Ogunlana
Requires-Python: >=3.13
Classifier: Programming Language :: Python :: 3
Classifier: Programming Language :: Python :: 3.13
Classifier: Programming Language :: Python :: 3.14
Requires-Dist: pandas (>=2.3.3,<3.0.0)
Requires-Dist: requests (>=2.32.5,<3.0.0)
